pyrsmq-0.6.1.dist-info/licenses/LICENSE
rsmq/__init__.py
rsmq/const.py
rsmq/consumer.py
rsmq/retry_delay_handler.py
rsmq/rsmq.py
rsmq/cmd/__init__.py
rsmq/cmd/base_command.py
rsmq/cmd/change_message_visibility.py
rsmq/cmd/create_queue.py
rsmq/cmd/delete_message.py
rsmq/cmd/delete_queue.py
rsmq/cmd/exceptions.py
rsmq/cmd/get_queue_attributes.py
rsmq/cmd/list_queues.py
rsmq/cmd/pop_message.py
rsmq/cmd/receive_message.py
rsmq/cmd/send_message.py
rsmq/cmd/set_queue_attributes.py
rsmq/cmd/utils.py
tests/__init__.py
tests/test_rsmq.py
tests/test_utils.py
pyrsmq-0.6.1.dist-info/METADATA
pyrsmq-0.6.1.dist-info/WHEEL
pyrsmq-0.6.1.dist-info/top_level.txt
pyrsmq-0.6.1.dist-info/RECORD
