Metadata-Version: 2.4
Name: PyRSMQ
Version: 0.6.1
Summary: Python Implementation of Redis SMQ
Home-page: https://mlasevich.github.io/PyRSMQ/
Author: Michael Lasevich
Author-email: mlasevich+pyrsmq@gmail.com
License: Apache 2.0
Classifier: Programming Language :: Python :: 3
Classifier: License :: OSI Approved :: Apache Software License
Classifier: Operating System :: OS Independent
Requires-Python: >=3.6
License-File: LICENSE
Requires-Dist: redis
Dynamic: author
Dynamic: author-email
Dynamic: classifier
Dynamic: description
Dynamic: description-content-type
Dynamic: home-page
Dynamic: license
Dynamic: license-file
Dynamic: requires-dist
Dynamic: requires-python
Dynamic: summary
